libmsym/__init__.py
libmsym/interfaces.py
libmsym/libmsym.so
libmsym/libmsym.so.0.2
libmsym/libmsym.so.0.2.4
libmsym/main.py
libmsym-0.2.4.2.dist-info/METADATA
libmsym-0.2.4.2.dist-info/WHEEL
libmsym-0.2.4.2.dist-info/top_level.txt
libmsym-0.2.4.2.dist-info/RECORD
