Metadata-Version: 2.1
Name: libmsym
Version: 0.2.4.2
Summary: libmsym python binding
Home-page: https://github.com/mcodev31/libmsym
Author: Marcus Johansson
Author-email: mcodev31@gmail.com
License: MIT
Platform: Linux
Platform: Darwin
